{
    "products":[
        {
          "id": 1,
          "name": "Product A",
          "description": "Description of Product A",
          "price": 29.99,
          "category": "Electronics",
          "image":"/Home1.jpg"
        },
        {
          "id": 2,
          "name": "Product B",
          "description": "Description of Product B",
          "price": 19.99,
          "category": "Clothing",
          "image":"/Home1.jpg"
        },
        {
          "id": 3,
          "name": "Product C",
          "description": "Description of Product C",
          "price": 39.99,
          "category": "Home Appliances",
          "image":"/Home1.jpg"
        },
        {
          "id": 4,
          "name": "Product D",
          "description": "Description of Product D",
          "price": 24.99,
          "category": "Toys",
          "image":"/Home1.jpg"
        },
        {
          "id": 5,
          "name": "Product E",
          "description": "Description of Product E",
          "price": 14.99,
          "category": "Books",
          "image":"/Home1.jpg"
        },
        {
          "id": 6,
          "name": "Product F",
          "description": "Description of Product F",
          "price": 49.99,
          "category": "Electronics",
          "image":"/Home1.jpg"
        },
        {
          "id": 7,
          "name": "Product G",
          "description": "Description of Product G",
          "price": 9.99,
          "category": "Clothing"
        },
        {
          "id": 8,
          "name": "Product H",
          "description": "Description of Product H",
          "price": 34.99,
          "category": "Home Appliances"
        },
        {
          "id": 9,
          "name": "Product I",
          "description": "Description of Product I",
          "price": 44.99,
          "category": "Toys"
        },
        {
          "id": 10,
          "name": "Product J",
          "description": "Description of Product J",
          "price": 19.99,
          "category": "Books"
        }
      ]
      
}